[{"key": "1号线", "value": "镇海路"}, {"key": "1号线", "value": "中山公园"}, {"key": "1号线", "value": "将军祠"}, {"key": "1号线", "value": "文灶"}, {"key": "1号线", "value": "湖滨东路"}, {"key": "1号线", "value": "莲坂"}, {"key": "1号线", "value": "莲花路口"}, {"key": "1号线", "value": "吕厝"}, {"key": "1号线", "value": "乌石浦"}, {"key": "1号线", "value": "塘边"}, {"key": "1号线", "value": "火炬园"}, {"key": "1号线", "value": "殿前"}, {"key": "1号线", "value": "高崎"}, {"key": "1号线", "value": "集美学村"}, {"key": "1号线", "value": "园博苑"}, {"key": "1号线", "value": "杏林村"}, {"key": "1号线", "value": "杏锦路"}, {"key": "1号线", "value": "官任"}, {"key": "1号线", "value": "诚毅广场"}, {"key": "1号线", "value": "集美软件园"}, {"key": "1号线", "value": "集美大道"}, {"key": "1号线", "value": "天水路"}, {"key": "1号线", "value": "厦门北站"}, {"key": "1号线", "value": "岩内"}, {"key": "2号线", "value": "天竺山"}, {"key": "2号线", "value": "东孚"}, {"key": "2号线", "value": "东瑶"}, {"key": "2号线", "value": "新阳大道"}, {"key": "2号线", "value": "新"}, {"key": "2号线", "value": "翁角路"}, {"key": "2号线", "value": "马青路"}, {"key": "2号线", "value": "海沧行政中心"}, {"key": "2号线", "value": "海沧商务中心"}, {"key": "2号线", "value": "海沧湾公园"}, {"key": "2号线", "value": "邮轮中心"}, {"key": "2号线", "value": "建业路"}, {"key": "2号线", "value": "湖滨中路"}, {"key": "2号线", "value": "体育中心"}, {"key": "2号线", "value": "育秀东路"}, {"key": "2号线", "value": "吕厝"}, {"key": "2号线", "value": "江头"}, {"key": "2号线", "value": "后埔"}, {"key": "2号线", "value": "蔡塘"}, {"key": "2号线", "value": "古地石"}, {"key": "2号线", "value": "岭兜"}, {"key": "2号线", "value": "软件园二期"}, {"key": "2号线", "value": "何厝"}, {"key": "2号线", "value": "观音山"}, {"key": "2号线", "value": "东宅"}, {"key": "2号线", "value": "两岸金融中心"}, {"key": "2号线", "value": "五通"}, {"key": "2号线", "value": "湿地公园"}, {"key": "2号线", "value": "钟宅"}, {"key": "2号线", "value": "五缘湾"}, {"key": "3号线", "value": "厦门火车站"}, {"key": "3号线", "value": "湖滨东路"}, {"key": "3号线", "value": "体育中心"}, {"key": "3号线", "value": "人才中心"}, {"key": "3号线", "value": "湖里公园"}, {"key": "3号线", "value": "华荣路"}, {"key": "3号线", "value": "火炬园"}, {"key": "3号线", "value": "小东山"}, {"key": "3号线", "value": "安兜"}, {"key": "3号线", "value": "坂尚"}, {"key": "3号线", "value": "湖里创新园"}, {"key": "3号线", "value": "五缘湾"}, {"key": "3号线", "value": "国际博览中心"}, {"key": "3号线", "value": "东界"}, {"key": "3号线", "value": "洪坑"}, {"key": "3号线", "value": "林前"}, {"key": "3号线", "value": "鼓锣"}, {"key": "3号线", "value": "翔安市民公园"}, {"key": "3号线", "value": "浦边"}, {"key": "3号线", "value": "后村"}, {"key": "3号线", "value": "蔡厝"}]